[{"symbol":"banf",
"low":null,
"high":null,
"volume":null},
{"symbol":"banf",
"date":"",
"open":null,
"high":null,
"low":null,
"volume":null},
{"symbol":"banf",
"date":"16:00",
"open":56.51,
"high":55.63,
"low":55.05,
"volume":52},
{"symbol":"banf",
"date":"04/05/2016",
"open":57.08,
"high":56.21,
"low":56.1,
"volume":20},
{"symbol":"banf",
"date":"04/04/2016",
"open":57.5,
"high":56.71,
"low":56.65,
"volume":15},
{"symbol":"banf",
"date":"04/01/2016",
"open":56.53,
"high":57.58,
"low":55.89,
"volume":11},
{"symbol":"banf",
"date":"03/31/2016",
"open":56.45,
"high":57.03,
"low":56.37,
"volume":15},
{"symbol":"banf",
"date":"03/30/2016",
"open":56.91,
"high":56.9,
"low":55.61,
"volume":12},
{"symbol":"banf",
"date":"03/29/2016",
"open":56.13,
"high":56.32,
"low":55.45,
"volume":50},
{"symbol":"banf",
"date":"03/28/2016",
"open":57.54,
"high":56.68,
"low":55.93,
"volume":20},
{"symbol":"banf",
"date":"03/24/2016",
"open":56.61,
"high":56.47,
"low":55.39,
"volume":20},
{"symbol":"banf",
"date":"03/23/2016",
"open":57.35,
"high":56.62,
"low":56.52,
"volume":25},
{"symbol":"banf",
"date":"03/22/2016",
"open":57.88,
"high":57.55,
"low":56.9,
"volume":17},
{"symbol":"banf",
"date":"03/21/2016",
"open":56.7633,
"high":57.81,
"low":56.7633,
"volume":19},
{"symbol":"banf",
"date":"03/18/2016",
"open":58.44,
"high":58.69,
"low":58.24,
"volume":70},
{"symbol":"banf",
"date":"03/17/2016",
"open":56.89,
"high":58.29,
"low":56.4,
"volume":15},
{"symbol":"banf",
"date":"03/16/2016",
"open":57.51,
"high":57.27,
"low":56.94,
"volume":13},
{"symbol":"banf",
"date":"03/15/2016",
"open":57.94,
"high":57.44,
"low":57.44,
"volume":9},
{"symbol":"banf",
"date":"03/14/2016",
"open":58.74,
"high":58.26,
"low":57.88,
"volume":13},
{"symbol":"banf",
"date":"03/11/2016",
"open":57.72,
"high":58.75,
"low":56.89,
"volume":23},
{"symbol":"banf",
"date":"03/10/2016",
"open":57.495,
"high":57.55,
"low":56.4035,
"volume":16},
{"symbol":"banf",
"date":"03/09/2016",
"open":58.62,
"high":57.43,
"low":57.17,
"volume":32},
{"symbol":"banf",
"date":"03/08/2016",
"open":58.33,
"high":58.06,
"low":53.39,
"volume":64},
{"symbol":"banf",
"date":"03/07/2016",
"open":59.257,
"high":58.98,
"low":58.63,
"volume":20},
{"symbol":"banf",
"date":"03/04/2016",
"open":60.06,
"high":59.57,
"low":58.93,
"volume":23},
{"symbol":"banf",
"date":"03/03/2016",
"open":59.1,
"high":60.02,
"low":58.5015,
"volume":28},
{"symbol":"banf",
"date":"03/02/2016",
"open":58.11,
"high":59.09,
"low":57.62,
"volume":40},
{"symbol":"banf",
"date":"03/01/2016",
"open":56.7,
"high":57.97,
"low":56.66,
"volume":7},
{"symbol":"banf",
"date":"02/29/2016",
"open":57.68,
"high":56.5,
"low":56.08,
"volume":36},
{"symbol":"banf",
"date":"02/26/2016",
"open":56.01,
"high":56.55,
"low":55,
"volume":19},
{"symbol":"banf",
"date":"02/25/2016",
"open":55,
"high":55.22,
"low":54.23,
"volume":34},
{"symbol":"banf",
"date":"02/24/2016",
"open":54.27,
"high":54.98,
"low":53.61,
"volume":11},
{"symbol":"banf",
"date":"02/23/2016",
"open":55.08,
"high":54.52,
"low":54.17,
"volume":12},
{"symbol":"banf",
"date":"02/22/2016",
"open":55.03,
"high":55.2,
"low":55,
"volume":17},
{"symbol":"banf",
"date":"02/19/2016",
"open":54.97,
"high":54.88,
"low":54.4,
"volume":11},
{"symbol":"banf",
"date":"02/18/2016",
"open":55.8,
"high":55,
"low":54.38,
"volume":13},
{"symbol":"banf",
"date":"02/17/2016",
"open":55.42,
"high":55.71,
"low":54.89,
"volume":21},
{"symbol":"banf",
"date":"02/16/2016",
"open":55.5,
"high":55.39,
"low":53.7078,
"volume":15},
{"symbol":"banf",
"date":"02/12/2016",
"open":55.5,
"high":55.03,
"low":53.77,
"volume":24},
{"symbol":"banf",
"date":"02/11/2016",
"open":54.4,
"high":55.05,
"low":54.109,
"volume":17},
{"symbol":"banf",
"date":"02/10/2016",
"open":55.73,
"high":55.09,
"low":54.96,
"volume":25},
{"symbol":"banf",
"date":"02/09/2016",
"open":54.43,
"high":55.16,
"low":54.22,
"volume":23},
{"symbol":"banf",
"date":"02/08/2016",
"open":53.74,
"high":54.84,
"low":53.62,
"volume":30},
{"symbol":"banf",
"date":"02/05/2016",
"open":54.91,
"high":54.21,
"low":54.2,
"volume":23},
{"symbol":"banf",
"date":"02/04/2016",
"open":55.27,
"high":54.74,
"low":54.39,
"volume":29},
{"symbol":"banf",
"date":"02/03/2016",
"open":55.6,
"high":55.15,
"low":53.93,
"volume":37},
{"symbol":"banf",
"date":"02/02/2016",
"open":55.27,
"high":54.92,
"low":54.65,
"volume":18},
{"symbol":"banf",
"date":"02/01/2016",
"open":55.61,
"high":55.7,
"low":54.21,
"volume":29},
{"symbol":"banf",
"date":"01/29/2016",
"open":53.82,
"high":55.94,
"low":53.76,
"volume":33},
{"symbol":"banf",
"date":"01/28/2016",
"open":53,
"high":53.82,
"low":53,
"volume":19},
{"symbol":"banf",
"date":"01/27/2016",
"open":52.04,
"high":52.5,
"low":51.25,
"volume":17},
{"symbol":"banf",
"date":"01/26/2016",
"open":51.17,
"high":52.34,
"low":51.17,
"volume":29},
{"symbol":"banf",
"date":"01/25/2016",
"open":53.24,
"high":51.19,
"low":51.14,
"volume":24},
{"symbol":"banf",
"date":"01/22/2016",
"open":54.21,
"high":53.33,
"low":52.72,
"volume":29},
{"symbol":"banf",
"date":"01/21/2016",
"open":54.53,
"high":54.21,
"low":53.41,
"volume":18},
{"symbol":"banf",
"date":"01/20/2016",
"open":53.2,
"high":54.26,
"low":52.52,
"volume":26},
{"symbol":"banf",
"date":"01/19/2016",
"open":54.09,
"high":53.87,
"low":53.296,
"volume":20},
{"symbol":"banf",
"date":"01/15/2016",
"open":54.08,
"high":54.05,
"low":53.01,
"volume":24},
{"symbol":"banf",
"date":"01/14/2016",
"open":55.71,
"high":55.215,
"low":54.795,
"volume":23},
{"symbol":"banf",
"date":"01/13/2016",
"open":56.8,
"high":55.21,
"low":55.09,
"volume":19},
{"symbol":"banf",
"date":"01/12/2016",
"open":57.79,
"high":57.29,
"low":57.11,
"volume":25},
{"symbol":"banf",
"date":"01/11/2016",
"open":56.69,
"high":57.22,
"low":56.37,
"volume":24},
{"symbol":"banf",
"date":"01/08/2016",
"open":57.24,
"high":56.13,
"low":56.02,
"volume":24},
{"symbol":"banf",
"date":"01/07/2016",
"open":56.46,
"high":56.66,
"low":56.46,
"volume":22},
{"symbol":"banf",
"date":"01/06/2016",
"open":56.25,
"high":57.76,
"low":56.25,
"volume":38},
{"symbol":"banf",
"date":"01/05/2016",
"open":56.85,
"high":56.75,
"low":56,
"volume":35}]